lexcorpora/__init__.py
lexcorpora/asset.py
lexcorpora/asset_artifact.py
lexcorpora/asset_concept.py
lexcorpora/non.py
lexcorpora/pre/__init__.py
lexcorpora/pre/build_abbreviations.py
lexcorpora/pre/build_digits.py
lexcorpora/pre/build_serials.py
lexcorpora/pre/patterns_axiom.py
lexcorpora/pre/patterns_date.py
lexcorpora/pre/patterns_docket.py
lexcorpora/pre/patterns_juridical.py
lexcorpora/pre/patterns_report.py
lexcorpora/pre/patterns_statute.py
lexcorpora/pre/patterns_unit.py
lexcorpora/pre/patterns_vs.py
lexcorpora/pre/utils.py
lexcorpora/tokenizer.py
lexcorpora-0.0.6.dist-info/METADATA
lexcorpora-0.0.6.dist-info/WHEEL
lexcorpora-0.0.6.dist-info/RECORD
